SFSGL/__init__.py
SFSGL/sfsgl.py
SFSGL/static/fa-solid-900.woff2
SFSGL/templates/file_gather.html
SFSGL/templates/file_share.html
SFSGL-0.1.8.dist-info/METADATA
SFSGL-0.1.8.dist-info/WHEEL
SFSGL-0.1.8.dist-info/top_level.txt
SFSGL-0.1.8.dist-info/RECORD
