Metadata-Version: 2.1
Name: SFSGL
Version: 0.1.8
Summary: Simple File Sharing and Gathering Library
Home-page: https://github.com/hasanaliozkan-dev/SFSGL/
Author: Hasan Ali Özkan
Project-URL: Source Code, https://github.com/hasanaliozkan-dev/SFSGL/
Project-URL: Bug Tracker, https://github.com/hasanaliozkan-dev/SFSGL/issues
Project-URL: Documentation, https://github.com/hasanaliozkan-dev/SFSGL/blob/main/README.md
Requires-Python: >=3.6
Requires-Dist: flask
Requires-Dist: werkzeug
